README.md
setup.py
generate_rospkg_apkbuild/APKBUILD.em.sh
generate_rospkg_apkbuild/__init__.py
generate_rospkg_apkbuild/genapkbuild.py
ros_abuild.egg-info/PKG-INFO
ros_abuild.egg-info/SOURCES.txt
ros_abuild.egg-info/dependency_links.txt
ros_abuild.egg-info/entry_points.txt
ros_abuild.egg-info/requires.txt
ros_abuild.egg-info/top_level.txt