Metadata-Version: 1.0
Name: ros-abuild
Version: 0.0.0
Summary: generate-rospkg-apkbuild
Home-page: https://github.com/alpine-ros/generate-rospkg-apkbuild
Author: Atsushi Watanabe
Author-email: atsushi.w@ieee.org
License: BSD
Platform: UNKNOWN
